spottedpy/__init__.py
spottedpy/access_individual_hotspots.py
spottedpy/hotspot_helper.py
spottedpy/main.py
spottedpy/neighbourhood_allinone_helper.py
spottedpy/neighbourhood_helper.py
spottedpy/neighbourhood_inner_outer_helper.py
spottedpy/neighbourhood_plotting.py
spottedpy/sensitivity_analysis.py
spottedpy/sp_plotting.py
spottedpy/tumour_perimeter.py
spottedpy-0.1.10.dist-info/LICENSE
spottedpy-0.1.10.dist-info/METADATA
spottedpy-0.1.10.dist-info/WHEEL
spottedpy-0.1.10.dist-info/top_level.txt
spottedpy-0.1.10.dist-info/RECORD
